{
  "db_name": "PostgreSQL",
  "query": "\n        WITH filtered_carts AS (\n            SELECT * FROM carts WHERE owner_id = $1 AND status = $2\n        ),\n        cart_line_items AS (\n            SELECT\n                x.*\n            FROM\n                filtered_carts,\n                JSONB_TO_RECORDSET(filtered_carts.items::JSONB) AS x(meal_id TEXT, quantity INTEGER)\n        ),\n        cart_items AS (\n            SELECT\n                cart_line_items.meal_id,\n                cart_line_items.quantity,\n                TO_JSONB(meals) AS meal,\n                TO_JSONB(kitchens) AS kitchen\n            FROM \n                filtered_carts,\n                cart_line_items\n            INNER JOIN meals ON meals.id = cart_line_items.meal_id\n            INNER JOIN kitchens ON kitchens.id = meals.kitchen_id\n        )\n        SELECT \n            filtered_carts.id,\n            filtered_carts.status,\n            filtered_carts.owner_id,\n            filtered_carts.created_at,\n            filtered_carts.updated_at,\n            JSONB_AGG(\n                cart_items\n            ) AS items\n        FROM\n            filtered_carts,\n            cart_items\n        GROUP BY\n            filtered_carts.id,\n            filtered_carts.status,\n            filtered_carts.owner_id,\n            filtered_carts.created_at,\n            filtered_carts.updated_at\n        ",
  "describe": {
    "columns": [
      {
        "ordinal": 0,
        "name": "id",
        "type_info": "Varchar"
      },
      {
        "ordinal": 1,
        "name": "status",
        "type_info": "Varchar"
      },
      {
        "ordinal": 2,
        "name": "owner_id",
        "type_info": "Varchar"
      },
      {
        "ordinal": 3,
        "name": "created_at",
        "type_info": "Timestamp"
      },
      {
        "ordinal": 4,
        "name": "updated_at",
        "type_info": "Timestamp"
      },
      {
        "ordinal": 5,
        "name": "items",
        "type_info": "Jsonb"
      }
    ],
    "parameters": {
      "Left": [
        "Text",
        "Text"
      ]
    },
    "nullable": [
      false,
      false,
      false,
      false,
      true,
      null
    ]
  },
  "hash": "4faed5c308efbf7cc45ff886e86e55088d088f6a08a582a07b6332eefe5ade11"
}
