{
  "db_name": "PostgreSQL",
  "query": "DELETE FROM meals WHERE id = $1 RETURNING *",
  "describe": {
    "columns": [
      {
        "ordinal": 0,
        "name": "id",
        "type_info": "Varchar"
      },
      {
        "ordinal": 1,
        "name": "name",
        "type_info": "Varchar"
      },
      {
        "ordinal": 2,
        "name": "description",
        "type_info": "Varchar"
      },
      {
        "ordinal": 3,
        "name": "price",
        "type_info": "Numeric"
      },
      {
        "ordinal": 4,
        "name": "rating",
        "type_info": "Numeric"
      },
      {
        "ordinal": 5,
        "name": "tags",
        "type_info": "Json"
      },
      {
        "ordinal": 6,
        "name": "cover_image_url",
        "type_info": "Varchar"
      },
      {
        "ordinal": 7,
        "name": "is_available",
        "type_info": "Bool"
      },
      {
        "ordinal": 8,
        "name": "kitchen_id",
        "type_info": "Varchar"
      },
      {
        "ordinal": 9,
        "name": "created_at",
        "type_info": "Timestamp"
      },
      {
        "ordinal": 10,
        "name": "updated_at",
        "type_info": "Timestamp"
      },
      {
        "ordinal": 11,
        "name": "likes",
        "type_info": "Int4"
      }
    ],
    "parameters": {
      "Left": [
        "Text"
      ]
    },
    "nullable": [
      false,
      false,
      false,
      false,
      false,
      false,
      false,
      false,
      false,
      false,
      true,
      false
    ]
  },
  "hash": "d59c6f90454fb3b40c2dcd0e2a7b92ca0270d79fa05f6ec0198c869901475168"
}
